shoalsoft/pants_opentelemetry_plugin/__init__.py
shoalsoft/pants_opentelemetry_plugin/exception_logging_processor.py
shoalsoft/pants_opentelemetry_plugin/opentelemetry_config.py
shoalsoft/pants_opentelemetry_plugin/opentelemetry_processor.py
shoalsoft/pants_opentelemetry_plugin/processor.py
shoalsoft/pants_opentelemetry_plugin/register.py
shoalsoft/pants_opentelemetry_plugin/single_threaded_processor.py
shoalsoft/pants_opentelemetry_plugin/subsystem.py
shoalsoft/pants_opentelemetry_plugin/workunit_handler.py
shoalsoft_pants_opentelemetry_plugin-0.5.0.dist-info/METADATA
shoalsoft_pants_opentelemetry_plugin-0.5.0.dist-info/WHEEL
shoalsoft_pants_opentelemetry_plugin-0.5.0.dist-info/namespace_packages.txt
shoalsoft_pants_opentelemetry_plugin-0.5.0.dist-info/top_level.txt
shoalsoft_pants_opentelemetry_plugin-0.5.0.dist-info/RECORD
