Metadata-Version: 2.4
Name: shoalsoft-pants-opentelemetry-plugin
Version: 0.5.0
Summary: Pantsbuild OpenTelemetry Plugin from Shoal Software LLC
Home-page: https://github.com/shoalsoft/shoalsoft-pants-opentelemetry-plugin
Author: Tom Dyas
Author-email: tom@shoalsoftware.com
Requires-Python: ==3.11.*
Requires-Dist: opentelemetry-api==1.34.1
Requires-Dist: opentelemetry-exporter-otlp==1.34.1
Requires-Dist: opentelemetry-sdk==1.34.1
Requires-Dist: packaging
Dynamic: author
Dynamic: author-email
Dynamic: description
Dynamic: description-content-type
Dynamic: home-page
Dynamic: requires-dist
Dynamic: requires-python
Dynamic: summary
